[{"id": 1, "isthing": true, "score": 0.9142704606056213, "category_id": 127, "instance_id": 0}, {"id": 2, "isthing": true, "score": 0.8966149091720581, "category_id": 117, "instance_id": 1}, {"id": 3, "isthing": true, "score": 0.7795493602752686, "category_id": 115, "instance_id": 2}, {"id": 4, "isthing": false, "category_id": 9, "area": 24875}, {"id": 5, "isthing": false, "category_id": 34, "area": 5939}, {"id": 6, "isthing": false, "category_id": 37, "area": 31997}, {"id": 7, "isthing": false, "category_id": 40, "area": 5183}, {"id": 8, "isthing": false, "category_id": 42, "area": 46719}, {"id": 9, "isthing": false, "category_id": 53, "area": 84613}]