[{"id": 1, "isthing": true, "score": 0.9948061108589172, "category_id": 111, "instance_id": 0}, {"id": 2, "isthing": true, "score": 0.9919806718826294, "category_id": 112, "instance_id": 1}, {"id": 3, "isthing": true, "score": 0.9713143706321716, "category_id": 115, "instance_id": 2}, {"id": 4, "isthing": true, "score": 0.9049283266067505, "category_id": 129, "instance_id": 3}, {"id": 5, "isthing": true, "score": 0.6254993677139282, "category_id": 117, "instance_id": 6}, {"id": 6, "isthing": false, "category_id": 9, "area": 24047}, {"id": 7, "isthing": false, "category_id": 40, "area": 20981}, {"id": 8, "isthing": false, "category_id": 43, "area": 9881}, {"id": 9, "isthing": false, "category_id": 53, "area": 151020}, {"id": 10, "isthing": false, "category_id": 54, "area": 13927}]